.eslintrc
.prettierrc.json
.stylelintignore
.stylelintrc.json
CHANGES.rst
CONTRIBUTORS.rst
Gruntfile.js
HOWTO_DEVELOP.rst
LICENSE
MANIFEST.in
README.rst
package.json
setup.cfg
setup.py
yarn.lock
docs/LICENSE.GPL
docs/LICENSE.rst
docs/index.rst
docs/migrationTo2.rst
src/redturtle/__init__.py
src/redturtle.agidtheme.egg-info/PKG-INFO
src/redturtle.agidtheme.egg-info/SOURCES.txt
src/redturtle.agidtheme.egg-info/dependency_links.txt
src/redturtle.agidtheme.egg-info/entry_points.txt
src/redturtle.agidtheme.egg-info/namespace_packages.txt
src/redturtle.agidtheme.egg-info/not-zip-safe
src/redturtle.agidtheme.egg-info/requires.txt
src/redturtle.agidtheme.egg-info/top_level.txt
src/redturtle/agidtheme/__init__.py
src/redturtle/agidtheme/configure.zcml
src/redturtle/agidtheme/interfaces.py
src/redturtle/agidtheme/setuphandlers.py
src/redturtle/agidtheme/testing.py
src/redturtle/agidtheme/vocabularies.py
src/redturtle/agidtheme/behaviors/__init__.py
src/redturtle/agidtheme/behaviors/behavior.py
src/redturtle/agidtheme/behaviors/configure.zcml
src/redturtle/agidtheme/browser/__init__.py
src/redturtle/agidtheme/browser/configure.zcml
src/redturtle/agidtheme/browser/tile_collection_renderers.py
src/redturtle/agidtheme/browser/viewlets.py
src/redturtle/agidtheme/browser/overrides/.gitkeep
src/redturtle/agidtheme/browser/overrides/Products.CMFPlone.browser.templates.main_template.pt
src/redturtle/agidtheme/browser/overrides/collective.editablemenu.browser.templates.custom_sections.pt
src/redturtle/agidtheme/browser/overrides/plone.app.layout.viewlets.footer.pt
src/redturtle/agidtheme/browser/overrides/plone.app.layout.viewlets.sections.pt
src/redturtle/agidtheme/browser/overrides/redturtle.tiles.management.browser.templates.tiles_view.pt
src/redturtle/agidtheme/browser/static/.gitkeep
src/redturtle/agidtheme/browser/templates/aree_tematiche.pt
src/redturtle/agidtheme/browser/templates/document_by_line.pt
src/redturtle/agidtheme/browser/templates/document_relateditems.pt
src/redturtle/agidtheme/browser/templates/header_banner.pt
src/redturtle/agidtheme/browser/templates/header_social_viewlet.pt
src/redturtle/agidtheme/browser/templates/leadimage.pt
src/redturtle/agidtheme/browser/templates/logo.pt
src/redturtle/agidtheme/browser/templates/news_area_tematica.pt
src/redturtle/agidtheme/browser/templates/news_big_photo_renderer.pt
