Metadata-Version: 1.1
Name: redturtle.agidtheme
Version: 2.2.3
Summary: Theme for Italia Design System
Home-page: https://github.com/PloneGov-IT/redturtle.agidtheme.git
Author: RedTurtle
Author-email: sviluppoplone@redturtle.it
License: GPL version 3
Keywords: Plone Italia Design System Theme
Platform: UNKNOWN
Classifier: Environment :: Web Environment
Classifier: Framework :: Plone
Classifier: Framework :: Plone :: 5.0
Classifier: Framework :: Plone :: 5.1
Classifier: Framework :: Plone :: Theme
Classifier: Programming Language :: Python
Classifier: Programming Language :: Python :: 2.7
Classifier: Operating System :: OS Independent
Classifier: License :: OSI Approved :: GNU General Public License v3 (GPLv3)
